.coveragerc
.editorconfig
.gitattributes
.gitignore
.gitlab-ci.yml
AUTHORS.rst
CONTRIBUTING.rst
HISTORY.rst
LICENSE
MANIFEST.in
Makefile
README.rst
pyproject.toml
tox.ini
.github/ISSUE_TEMPLATE.md
docs/Makefile
docs/authors.rst
docs/conf.py
docs/contributing.rst
docs/history.rst
docs/index.rst
docs/installation.rst
docs/make.bat
docs/readme.rst
docs/usage.rst
docs/_build/html/_static/file.png
docs/_build/html/_static/minus.png
docs/_build/html/_static/plus.png
examples/notebooks/features_and_usage.ipynb
geoarray/__init__.py
geoarray/baseclasses.py
geoarray/masks.py
geoarray/metadata.py
geoarray/subsetting.py
geoarray/version.py
geoarray.egg-info/PKG-INFO
geoarray.egg-info/SOURCES.txt
geoarray.egg-info/dependency_links.txt
geoarray.egg-info/not-zip-safe
geoarray.egg-info/requires.txt
geoarray.egg-info/top_level.txt