Metadata-Version: 2.4
Name: geoarray
Version: 0.19.2
Summary: Fast Python interface for geodata - either on disk or in memory
Author-email: Daniel Scheffler <daniel.scheffler@gfz.de>
License-Expression: Apache-2.0
Project-URL: Source code, https://git.gfz-potsdam.de/danschef/geoarray
Project-URL: Issue Tracker, https://git.gfz-potsdam.de/danschef/geoarray/-/issues
Project-URL: Documentation, https://danschef.git-pages.gfz-potsdam.de/geoarray/doc/
Project-URL: Change log, https://git.gfz-potsdam.de/danschef/geoarray/-/blob/main/HISTORY.rst
Keywords: geoarray,geoprocessing,gdal,numpy
Classifier: Development Status :: 4 - Beta
Classifier: Intended Audience :: Developers
Classifier: Natural Language :: English
Classifier: Programming Language :: Python :: 3.8
Classifier: Programming Language :: Python :: 3.9
Classifier: Programming Language :: Python :: 3.10
Classifier: Programming Language :: Python :: 3.11
Classifier: Programming Language :: Python :: 3.12
Requires-Python: >=3.8
License-File: LICENSE
License-File: AUTHORS.rst
Requires-Dist: cartopy>=0.20
Requires-Dist: dill
Requires-Dist: gdal>=3.8.0
Requires-Dist: matplotlib
Requires-Dist: numpy
Requires-Dist: pandas
Requires-Dist: py_tools_ds>=0.19.0
Requires-Dist: scikit-image
Requires-Dist: shapely
Provides-Extra: interactive-plotting
Requires-Dist: folium; extra == "interactive-plotting"
Requires-Dist: geojson; extra == "interactive-plotting"
Requires-Dist: holoviews>1.12.7; extra == "interactive-plotting"
Provides-Extra: doc
Requires-Dist: sphinx-argparse; extra == "doc"
Requires-Dist: sphinx_rtd_theme; extra == "doc"
Provides-Extra: test
Requires-Dist: pytest; extra == "test"
Requires-Dist: pytest-cov; extra == "test"
Requires-Dist: pytest-reporter-html1; extra == "test"
Requires-Dist: urlchecker; extra == "test"
Requires-Dist: parameterized; extra == "test"
Provides-Extra: lint
Requires-Dist: flake8; extra == "lint"
Requires-Dist: pycodestyle; extra == "lint"
Requires-Dist: pydocstyle; extra == "lint"
Provides-Extra: dev
Requires-Dist: geoarray[test]; extra == "dev"
Requires-Dist: geoarray[doc]; extra == "dev"
Requires-Dist: geoarray[lint]; extra == "dev"
Dynamic: license-file
